body_composition/__init__.py
body_composition/batch_cli.py
body_composition/cli.py
body_composition/processor.py
body_composition/python_api.py
body_composition/python_batch_api.py
body_composition/utils/__init__.py
body_composition/utils/calculate_changes.py
body_composition/utils/dicom2nifti.py
body_composition/utils/extract_vertebral_body.py
body_composition/utils/run_total_segmentator.py
body_composition/utils/vol_and_int_extraction.py
body_composition_analysis-0.2.1.dist-info/LICENSE
body_composition_analysis-0.2.1.dist-info/METADATA
body_composition_analysis-0.2.1.dist-info/WHEEL
body_composition_analysis-0.2.1.dist-info/entry_points.txt
body_composition_analysis-0.2.1.dist-info/top_level.txt
body_composition_analysis-0.2.1.dist-info/RECORD
